Workbook

Sheet ListOfOrders
A1: Order ID | B1: Order Date | C1: Customer Name | D1: Segment
A2: BN-2011-7407039 | B2: 40544 | C2: Ruby Patel | D2: Home Office
A3: AZ-2011-9050313 | B3: 40546 | C3: Summer Hayward | D3: Consumer
A4: AZ-2011-6674300 | B4: 40547 | C4: Devin Huddleston | D4: Consumer
A5: BN-2011-2819714 | B5: 40547 | C5: Mary Parker | D5: Corporate
A6: AZ-2011-617423 | B6: 40548 | C6: Daniel Burke | D6: Home Office
A7: AZ-2011-2918397 | B7: 40550 | C7: Fredrick Beveridge | D7: Corporate
A8: BN-2011-3248724 | B8: 40551 | C8: Archer Hort | D8: Consumer
A9: AZ-2011-6712797 | B9: 40554 | C9: Evie Flockhart | D9: Consumer
A10: AZ-2011-4827146 | B10: 40554 | C10: Faith Greenwood | D10: Consumer
A11: AZ-2011-6439906 | B11: 40554 | C11: Summer Hayward | D11: Consumer
A12: AZ-2011-7053593 | B12: 40554 | C12: Gracie Powell | D12: Consumer
A13: AZ-2011-5702370 | B13: 40555 | C13: Hershel Snyder | D13: Corporate
... A501: AZ-2011-3958316 | B501: 40808 | C501: Xavier Martindale | D501: Consumer

Sheet OrderBreakdown
A1: Order ID | B1: Product Name | C1: Discount | D1: Sales | E1: Profit | F1: Quantity | G1: Category | H1: Sub-Category | I1: date
A2: BN-2011-7407039 | B2: Enermax Note Cards, Premium | C2: 0.5 | D2: 45 | E2: -26 | F2: 3 | G2: Office Supplies | H2: Paper | I2: =VLOOKUP(A2,ListOfOrders!$A:$B,2,0) -> 40544
A3: AZ-2011-9050313 | B3: Dania Corner Shelving, Traditional | C3: 0 | D3: 854 | E3: 290 | F3: 7 | G3: Furniture | H3: Bookcases | I3: =VLOOKUP(A3,ListOfOrders!$A:$B,2,0) -> 40546
A4: AZ-2011-6674300 | B4: Binney & Smith Sketch Pad, Easy-Erase | C4: 0 | D4: 140 | E4: 21 | F4: 3 | G4: Office Supplies | H4: Art | I4: =VLOOKUP(A4,ListOfOrders!$A:$B,2,0) -> 40547
A5: BN-2011-2819714 | B5: Boston Markers, Easy-Erase | C5: 0.5 | D5: 27 | E5: -22 | F5: 2 | G5: Office Supplies | H5: Art | I5: =VLOOKUP(A5,ListOfOrders!$A:$B,2,0) -> 40547
A6: BN-2011-2819714 | B6: Eldon Folders, Single Width | C6: 0.5 | D6: 17 | E6: -1 | F6: 2 | G6: Office Supplies | H6: Storage | I6: =VLOOKUP(A6,ListOfOrders!$A:$B,2,0) -> 40547
A7: AZ-2011-617423 | B7: Binney & Smith Pencil Sharpener, Water Color | C7: 0 | D7: 90 | E7: 21 | F7: 3 | G7: Office Supplies | H7: Art | I7: =VLOOKUP(A7,ListOfOrders!$A:$B,2,0) -> 40548
A8: AZ-2011-617423 | B8: Sanford Canvas, Fluorescent | C8: 0 | D8: 207 | E8: 77 | F8: 4 | G8: Office Supplies | H8: Art | I8: =VLOOKUP(A8,ListOfOrders!$A:$B,2,0) -> 40548
A9: AZ-2011-2918397 | B9: Bush Floating Shelf Set, Pine | C9: 0.1 | D9: 155 | E9: 36 | F9: 1 | G9: Furniture | H9: Bookcases | I9: =VLOOKUP(A9,ListOfOrders!$A:$B,2,0) -> 40550
A10: AZ-2011-2918397 | B10: Accos Thumb Tacks, Assorted Sizes | C10: 0 | D10: 33 | E10: 2 | F10: 3 | G10: Office Supplies | H10: Fasteners | I10: =VLOOKUP(A10,ListOfOrders!$A:$B,2,0) -> 40550
A11: AZ-2011-2918397 | B11: Smead Lockers, Industrial | C11: 0.1 | D11: 716 | E11: 143 | F11: 4 | G11: Office Supplies | H11: Storage | I11: =VLOOKUP(A11,ListOfOrders!$A:$B,2,0) -> 40550
A12: BN-2011-3248724 | B12: Ikea Classic Bookcase, Metal | C12: 0.6 | D12: 987 | E12: -1012 | F12: 6 | G12: Furniture | H12: Bookcases | I12: =VLOOKUP(A12,ListOfOrders!$A:$B,2,0) -> 40551
A13: BN-2011-3248724 | B13: Binney & Smith Sketch Pad, Blue | C13: 0.5 | D13: 116 | E13: -56 | F13: 5 | G13: Office Supplies | H13: Art | I13: =VLOOKUP(A13,ListOfOrders!$A:$B,2,0) -> 40551
... A952: AZ-2011-2859436 | B952: StarTech Calculator, White | C952: 0 | D952: 115 | E952: 2 | F952: 3 | G952: Technology | H952: Machines | I952: =VLOOKUP(A952,ListOfOrders!$A:$B,2,0) -> 40808

Sheet SalesTargets
A1: Month of Order | B1: Category | C1: Target
A2: 40544 | B2: Furniture | C2: 15000
A3: 40575 | B3: Furniture | C3: 20000
A4: 40603 | B4: Furniture | C4: 18000
A5: 40634 | B5: Furniture | C5: 10400
A6: 40664 | B6: Furniture | C6: 10500
A7: 40695 | B7: Furniture | C7: 10600
A8: 40725 | B8: Furniture | C8: 10800
A9: 40756 | B9: Furniture | C9: 10900
A10: 40787 | B10: Furniture | C10: 11000
A11: 40544 | B11: Office Supplies | C11: 16000
A12: 40575 | B12: Office Supplies | C12: 18000
A13: 40603 | B13: Office Supplies | C13: 5000
... A28: 40787 | B28: Technology | C28: 9000
